LICENSE
MANIFEST.in
OSIx.py
README.md
pyproject.toml
setup.py
OSIx.egg-info/PKG-INFO
OSIx.egg-info/SOURCES.txt
OSIx.egg-info/dependency_links.txt
OSIx.egg-info/requires.txt
OSIx.egg-info/top_level.txt
core/__init__.py
core/base_module.py
core/base_username_data_digger.py
core/bs4_helper.py
core/chrome_driver_manager.py
core/constants.py
core/dir_manager.py
core/http_manager.py
core/resources_manager.py
core/temp_file.py
modules/__init__.py
modules/bitcoin_wallet.py
modules/bitcoin_wallet_graph.py
modules/github_username_data_digger.py
modules/http_navigation_manager.py
modules/input_args_handler.py
modules/state_file_handler.py
modules/temp_file_manager.py
modules/username_handler.py
resources/username_scanner_targets.json
resources/username_scanner_targets_nsfw.json