Metadata-Version: 2.1
Name: OSIx
Version: 0.4.2
Summary: Open Source Intelligence eXplorer.
Home-page: https://github.com/guibacellar/OSIx/
Author: Th3 0bservator
Author-email: th30bservator@gmail.com
License: Apache-2.0
Project-URL: Bug Tracker, https://github.com/guibacellar/OSIx/issues
Project-URL: Documentation, https://github.com/guibacellar/OSIx/blob/develop/README.md
Project-URL: Source Code, https://github.com/guibacellar/OSIx/
Platform: UNKNOWN
Classifier: Environment :: Console
Classifier: Natural Language :: English
Classifier: Operating System :: OS Independent
Classifier: Programming Language :: Python :: 3 :: Only
Classifier: Programming Language :: Python :: 3.6
Classifier: Programming Language :: Python :: 3.7
Classifier: Programming Language :: Python :: 3.8
Classifier: Topic :: Security
Classifier: Topic :: Utilities
Requires-Python: >=3.7.6
License-File: LICENSE
